<?xml version="1.0" encoding="UTF-8" ?>
<sect1 version="5.0" xmlns="http://docbook.org/ns/docbook" xmlns:ns6="http://www.w3.org/1999/xlink" xmlns:ns5="http://www.w3.org/1999/xhtml" xmlns:ns4="http://www.w3.org/2000/svg" xmlns:ns3="http://www.w3.org/1998/Math/MathML" xmlns:ns="http://docbook.org/ns/docbook" >
  <title>MapCreator</title>
  <subtitle>Eine Komponenten zur Visualisierung eines Einzugsgebietes.</subtitle>
  <informaltable>
    <tgroup cols="2">
      <colspec colname="c1" colnum="1" colwidth="1*"/>
      <colspec colname="c2" colnum="2" colwidth="3*"/>
      <thead>
        <row>
          <entry nameend="c2" namest="c1">Metainformation</entry>
        </row>
      </thead>
      <tbody>
        <row>
          <entry>Klassifikation</entry>
          <entry>Visualisierung</entry>
        </row>
      </tbody>
    </tgroup>
  </informaltable>
  <sect2>
    <title>Variablen</title>
  <informaltable>
    <tgroup cols="2">
      <colspec colname="c1" colnum="1" colwidth="1*"/>
      <colspec colname="c2" colnum="2" colwidth="3*"/>
      <thead>
        <row>
          <entry>Name</entry>
          <entry>Beschreibung</entry>
        </row>
      </thead>
      <tbody>
        <row>
          <entry>stylesFileName</entry>
          <entry>Name der Datei die den sld Style enthält</entry>
        </row>
        <row>
          <entry>styleID</entry>
          <entry>ID des Styles der zur Darstellung verwendet werden soll.</entry>
        </row>
        <row>
          <entry>hrus</entry>
          <entry>HRU Entities</entry>
        </row>
        <row>
          <entry>showAttr</entry>
          <entry>Liste der Attribute die dargestellt werden</entry>
        </row>
        <row>
          <entry>numOfRanges</entry>
          <entry>Anzahl der Intervalle zur Klassifikation der Attribute</entry>
        </row>
        <row>
          <entry>rangeColor</entry>
          <entry>Farbe zum Ausfüllen der Intervalle</entry>
        </row>
        <row>
          <entry>shapeFileName1</entry>
          <entry>Name eines Shapefiles zur Darstellung zusätzlicher Layer</entry>
        </row>
        <row>
          <entry>shapeFileName2</entry>
          <entry>Name eines Shapefiles zur Darstellung zusätzlicher Layer</entry>
        </row>
        <row>
          <entry>shapeFileName3</entry>
          <entry>Name eines Shapefiles zur Darstellung zusätzlicher Layer</entry>
        </row>
        <row>
          <entry>shapeColors</entry>
          <entry>Farben für zusätzliche Shapefiles</entry>
        </row>
      </tbody>
    </tgroup>
  </informaltable>
  </sect2>
  <sect2>
    <title>Beschreibung der Komponente</title>
    <para>Erstellt eine interaktive Visualisierung des Einzugsgebietes. Räumlich
      ausgeprägte Attribute der HRUs können dargestellt werden und entsprechende
      Legenden sind verfügbar. Ausserdem stehen grundlegende Funktionen eines
      typischen Geodaten-Viewers zur Auswahl, z.B. Karte bewegen, Hinein- bzw.
      Heraus-Zoomen und Selektion. Der Darstellungsstil der zu visualisierenden
      Attribute kann über eine sld Datei und Farbwerte angepasst werden.
      Zusätzliche Shape-Layer können hinzu geladen werden. Ein Export-Tool
      ermöglicht, dass die jeweils dargestellten Attribute (zzgl. weiterer
      Attribute des Ausgangs-Shapes) in ein neues Shapefile geschrieben
      werden.
    </para>
  </sect2>
</sect1>
